<people>

  <person>
    <firstname>Edith</firstname>
    <lastname>Andersson</lastname>
    <often>7</often>
    <Age>15</Age>
  </person>

  <person>
    <firstname>Edith</firstname>
    <lastname>Andersson</lastname>
    <often>7</often>
    <Age>15</Age>
  </person>

  <person>
    <firstname>Elsa</firstname>
    <lastname>Edvardsson</lastname>
    <often>1</often>
    <Age>15</Age>
  </person>

  <person>
    <firstname>Elsa</firstname>
    <lastname>Edvardsson</lastname>
    <often>1</often>
    <Age>15</Age>
  </person>

  <person>
    <firstname>Jacob</firstname>
    <lastname>Kjörk</lastname>
    <often>6</often>
    <Age>50</Age>
  </person>

  <person>
    <firstname></firstname>
    <lastname></lastname>
    <often>undefined</often>
    <Age></Age>
  </person>

  <person>
    <firstname></firstname>
    <lastname></lastname>
    <often>undefined</often>
    <Age></Age>
  </person>

  <person>
    <firstname></firstname>
    <lastname></lastname>
    <often>undefined</often>
    <Age></Age>
  </person>

  <person>
    <firstname></firstname>
    <lastname></lastname>
    <often>undefined</often>
    <Age></Age>
  </person>

  <person>
    <firstname></firstname>
    <lastname></lastname>
    <often>undefined</often>
    <Age></Age>
  </person>

  <person>
    <firstname></firstname>
    <lastname></lastname>
    <often>undefined</often>
    <Age></Age>
  </person>
</people>